stable_matching_sunder/__init__.py
stable_matching_sunder/matching.py
stable_matching_sunder-0.0.4.dist-info/METADATA
stable_matching_sunder-0.0.4.dist-info/WHEEL
stable_matching_sunder-0.0.4.dist-info/licenses/LICENSE
stable_matching_sunder-0.0.4.dist-info/RECORD
